[{"id":1,"sensor_id":1,"ambient_light":149.0,"temperature":19.3,"date":"2020-12-22T08:51:15.000+00:00","a_pressure":1009.0},{"id":2,"sensor_id":2,"ambient_light":8.0,"temperature":11.6,"date":"2020-12-22T08:53:05.000+00:00","a_pressure":1006.0},{"id":3,"sensor_id":3,"ambient_light":25.0,"temperature":-0.4,"date":"2020-12-22T08:53:13.000+00:00","a_pressure":1004.5},{"id":4,"sensor_id":4,"ambient_light":133.0,"temperature":24.5,"date":"2020-12-22T08:53:56.000+00:00","a_pressure":1005.0},{"id":5,"sensor_id":1,"ambient_light":143.0,"temperature":19.3,"date":"2020-12-22T08:54:41.000+00:00","a_pressure":1009.0},{"id":6,"sensor_id":2,"ambient_light":7.0,"temperature":11.2,"date":"2020-12-22T08:56:20.000+00:00","a_pressure":1006.5},{"id":7,"sensor_id":3,"ambient_light":35.0,"temperature":-0.3,"date":"2020-12-22T08:56:38.000+00:00","a_pressure":1004.5},{"id":8,"sensor_id":4,"ambient_light":124.0,"temperature":24.6,"date":"2020-12-22T08:57:21.000+00:00","a_pressure":1005.0},{"id":9,"sensor_id":1,"ambient_light":149.0,"temperature":19.3,"date":"2020-12-22T08:58:06.000+00:00","a_pressure":1009.0},{"id":10,"sensor_id":3,"ambient_light":15.0,"temperature":-0.3,"date":"2020-12-22T09:00:04.000+00:00","a_pressure":1004.5},{"id":11,"sensor_id":4,"ambient_light":109.0,"temperature":24.5,"date":"2020-12-22T09:00:47.000+00:00","a_pressure":1005.0},{"id":12,"sensor_id":1,"ambient_light":159.0,"temperature":19.2,"date":"2020-12-22T09:01:32.000+00:00","a_pressure":1009.0},{"id":13,"sensor_id":3,"ambient_light":30.0,"temperature":-0.4,"date":"2020-12-22T09:03:29.000+00:00","a_pressure":1004.5},{"id":14,"sensor_id":1,"ambient_light":160.0,"temperature":19.2,"date":"2020-12-22T09:04:57.000+00:00","a_pressure":1009.0},{"id":15,"sensor_id":3,"ambient_light":14.0,"temperature":-0.4,"date":"2020-12-22T09:06:55.000+00:00","a_pressure":1004.5},{"id":16,"sensor_id":4,"ambient_light":151.0,"temperature":24.5,"date":"2020-12-22T09:07:38.000+00:00","a_pressure":1005.0},{"id":17,"sensor_id":3,"ambient_light":4.0,"temperature":-0.3,"date":"2020-12-22T09:10:20.000+00:00","a_pressure":1004.5},{"id":18,"sensor_id":4,"ambient_light":160.0,"temperature":24.6,"date":"2020-12-22T09:11:03.000+00:00","a_pressure":1005.0},{"id":19,"sensor_id":2,"ambient_light":9.0,"temperature":12.1,"date":"2020-12-22T09:12:38.000+00:00","a_pressure":1006.5},{"id":20,"sensor_id":3,"ambient_light":12.0,"temperature":-0.1,"date":"2020-12-22T09:13:46.000+00:00","a_pressure":1004.5},{"id":21,"sensor_id":4,"ambient_light":145.0,"temperature":24.5,"date":"2020-12-22T09:14:29.000+00:00","a_pressure":1005.0},{"id":22,"sensor_id":1,"ambient_light":150.0,"temperature":19.2,"date":"2020-12-22T09:15:14.000+00:00","a_pressure":1009.0},{"id":23,"sensor_id":2,"ambient_light":10.0,"temperature":11.9,"date":"2020-12-22T09:15:53.000+00:00","a_pressure":1006.5},{"id":24,"sensor_id":3,"ambient_light":16.0,"temperature":-0.3,"date":"2020-12-22T09:17:11.000+00:00","a_pressure":1004.5},{"id":25,"sensor_id":4,"ambient_light":144.0,"temperature":24.0,"date":"2020-12-22T09:17:54.000+00:00","a_pressure":1005.5},{"id":26,"sensor_id":1,"ambient_light":154.0,"temperature":19.3,"date":"2020-12-22T09:18:40.000+00:00","a_pressure":1009.0},{"id":27,"sensor_id":2,"ambient_light":7.0,"temperature":12.3,"date":"2020-12-22T09:19:09.000+00:00","a_pressure":1007.0},{"id":28,"sensor_id":3,"ambient_light":21.0,"temperature":-0.1,"date":"2020-12-22T09:20:37.000+00:00","a_pressure":1004.5},{"id":29,"sensor_id":4,"ambient_light":131.0,"temperature":24.1,"date":"2020-12-22T09:21:20.000+00:00","a_pressure":1005.5},{"id":30,"sensor_id":1,"ambient_light":148.0,"temperature":19.2,"date":"2020-12-22T09:22:05.000+00:00","a_pressure":1009.0},{"id":31,"sensor_id":2,"ambient_light":6.0,"temperature":12.1,"date":"2020-12-22T09:22:25.000+00:00","a_pressure":1007.0},{"id":32,"sensor_id":3,"ambient_light":12.0,"temperature":-0.2,"date":"2020-12-22T09:24:02.000+00:00","a_pressure":1005.0},{"id":33,"sensor_id":4,"ambient_light":124.0,"temperature":24.2,"date":"2020-12-22T09:24:46.000+00:00","a_pressure":1005.5},{"id":34,"sensor_id":1,"ambient_light":151.0,"temperature":19.2,"date":"2020-12-22T09:25:31.000+00:00","a_pressure":1009.5},{"id":35,"sensor_id":3,"ambient_light":12.0,"temperature":-0.3,"date":"2020-12-22T09:27:28.000+00:00","a_pressure":1005.0},{"id":36,"sensor_id":4,"ambient_light":139.0,"temperature":24.5,"date":"2020-12-22T09:28:11.000+00:00","a_pressure":1005.5},{"id":37,"sensor_id":2,"ambient_light":9.0,"temperature":12.0,"date":"2020-12-22T09:28:56.000+00:00","a_pressure":1007.0},{"id":38,"sensor_id":1,"ambient_light":147.0,"temperature":19.2,"date":"2020-12-22T09:28:56.000+00:00","a_pressure":1009.5},{"id":39,"sensor_id":3,"ambient_light":8.0,"temperature":-0.4,"date":"2020-12-22T09:30:54.000+00:00","a_pressure":1005.0},{"id":40,"sensor_id":4,"ambient_light":149.0,"temperature":24.4,"date":"2020-12-22T09:31:37.000+00:00","a_pressure":1005.5},{"id":41,"sensor_id":2,"ambient_light":7.0,"temperature":12.5,"date":"2020-12-22T09:32:11.000+00:00","a_pressure":1007.0},{"id":42,"sensor_id":1,"ambient_light":151.0,"temperature":19.1,"date":"2020-12-22T09:32:22.000+00:00","a_pressure":1009.5},{"id":43,"sensor_id":3,"ambient_light":9.0,"temperature":-0.2,"date":"2020-12-22T09:34:19.000+00:00","a_pressure":1005.0},{"id":44,"sensor_id":4,"ambient_light":148.0,"temperature":24.5,"date":"2020-12-22T09:35:02.000+00:00","a_pressure":1005.5},{"id":45,"sensor_id":2,"ambient_light":6.0,"temperature":11.2,"date":"2020-12-22T09:35:27.000+00:00","a_pressure":1007.5},{"id":46,"sensor_id":1,"ambient_light":138.0,"temperature":19.1,"date":"2020-12-22T09:35:47.000+00:00","a_pressure":1009.5},{"id":47,"sensor_id":3,"ambient_light":18.0,"temperature":-0.5,"date":"2020-12-22T09:37:45.000+00:00","a_pressure":1005.0},{"id":48,"sensor_id":4,"ambient_light":146.0,"temperature":24.5,"date":"2020-12-22T09:38:28.000+00:00","a_pressure":1005.5},{"id":49,"sensor_id":2,"ambient_light":7.0,"temperature":11.6,"date":"2020-12-22T09:38:42.000+00:00","a_pressure":1007.5},{"id":50,"sensor_id":1,"ambient_light":142.0,"temperature":19.2,"date":"2020-12-22T09:39:13.000+00:00","a_pressure":1010.0},{"id":51,"sensor_id":3,"ambient_light":16.0,"temperature":-0.5,"date":"2020-12-22T09:41:10.000+00:00","a_pressure":1005.0},{"id":52,"sensor_id":4,"ambient_light":135.0,"temperature":24.4,"date":"2020-12-22T09:41:53.000+00:00","a_pressure":1006.0},{"id":53,"sensor_id":2,"ambient_light":7.0,"temperature":11.6,"date":"2020-12-22T09:41:58.000+00:00","a_pressure":1007.5},{"id":54,"sensor_id":1,"ambient_light":144.0,"temperature":19.1,"date":"2020-12-22T09:42:38.000+00:00","a_pressure":1010.0},{"id":55,"sensor_id":3,"ambient_light":18.0,"temperature":-0.5,"date":"2020-12-22T09:44:36.000+00:00","a_pressure":1005.0},{"id":56,"sensor_id":2,"ambient_light":9.0,"temperature":11.7,"date":"2020-12-22T09:45:13.000+00:00","a_pressure":1007.5},{"id":57,"sensor_id":4,"ambient_light":149.0,"temperature":24.4,"date":"2020-12-22T09:45:19.000+00:00","a_pressure":1006.0},{"id":58,"sensor_id":1,"ambient_light":144.0,"temperature":19.1,"date":"2020-12-22T09:46:04.000+00:00","a_pressure":1010.0},{"id":59,"sensor_id":3,"ambient_light":10.0,"temperature":-0.5,"date":"2020-12-22T09:48:01.000+00:00","a_pressure":1005.5},{"id":60,"sensor_id":2,"ambient_light":7.0,"temperature":12.0,"date":"2020-12-22T09:48:29.000+00:00","a_pressure":1007.5},{"id":61,"sensor_id":4,"ambient_light":150.0,"temperature":24.5,"date":"2020-12-22T09:48:44.000+00:00","a_pressure":1006.0},{"id":62,"sensor_id":1,"ambient_light":142.0,"temperature":19.0,"date":"2020-12-22T09:49:29.000+00:00","a_pressure":1010.0},{"id":63,"sensor_id":3,"ambient_light":9.0,"temperature":-0.4,"date":"2020-12-22T09:51:27.000+00:00","a_pressure":1005.5},{"id":64,"sensor_id":2,"ambient_light":10.0,"temperature":12.2,"date":"2020-12-22T09:51:44.000+00:00","a_pressure":1007.5},{"id":65,"sensor_id":4,"ambient_light":148.0,"temperature":24.4,"date":"2020-12-22T09:52:10.000+00:00","a_pressure":1006.0},{"id":66,"sensor_id":1,"ambient_light":140.0,"temperature":18.9,"date":"2020-12-22T09:52:55.000+00:00","a_pressure":1010.0},{"id":67,"sensor_id":3,"ambient_light":9.0,"temperature":-0.3,"date":"2020-12-22T09:54:52.000+00:00","a_pressure":1005.5},{"id":68,"sensor_id":2,"ambient_light":9.0,"temperature":12.4,"date":"2020-12-22T09:55:00.000+00:00","a_pressure":1007.5},{"id":69,"sensor_id":4,"ambient_light":146.0,"temperature":24.4,"date":"2020-12-22T09:55:35.000+00:00","a_pressure":1006.0},{"id":70,"sensor_id":1,"ambient_light":141.0,"temperature":18.9,"date":"2020-12-22T09:56:20.000+00:00","a_pressure":1010.0},{"id":71,"sensor_id":2,"ambient_light":12.0,"temperature":12.7,"date":"2020-12-22T09:58:15.000+00:00","a_pressure":1008.0},{"id":72,"sensor_id":3,"ambient_light":12.0,"temperature":-0.5,"date":"2020-12-22T09:58:18.000+00:00","a_pressure":1005.5},{"id":73,"sensor_id":4,"ambient_light":160.0,"temperature":24.2,"date":"2020-12-22T09:59:01.000+00:00","a_pressure":1006.0},{"id":74,"sensor_id":1,"ambient_light":162.0,"temperature":19.0,"date":"2020-12-22T09:59:46.000+00:00","a_pressure":1010.0},{"id":75,"sensor_id":2,"ambient_light":12.0,"temperature":12.3,"date":"2020-12-22T10:01:31.000+00:00","a_pressure":1007.5},{"id":76,"sensor_id":3,"ambient_light":15.0,"temperature":-0.5,"date":"2020-12-22T10:01:43.000+00:00","a_pressure":1005.5},{"id":77,"sensor_id":4,"ambient_light":155.0,"temperature":24.4,"date":"2020-12-22T10:02:26.000+00:00","a_pressure":1006.0},{"id":78,"sensor_id":1,"ambient_light":170.0,"temperature":19.0,"date":"2020-12-22T10:03:11.000+00:00","a_pressure":1010.0},{"id":79,"sensor_id":2,"ambient_light":11.0,"temperature":12.5,"date":"2020-12-22T10:04:46.000+00:00","a_pressure":1008.0},{"id":80,"sensor_id":3,"ambient_light":16.0,"temperature":-0.5,"date":"2020-12-22T10:05:09.000+00:00","a_pressure":1005.5},{"id":81,"sensor_id":4,"ambient_light":152.0,"temperature":24.6,"date":"2020-12-22T10:09:17.000+00:00","a_pressure":1006.5},{"id":82,"sensor_id":1,"ambient_light":178.0,"temperature":19.0,"date":"2020-12-22T10:10:02.000+00:00","a_pressure":1010.0},{"id":83,"sensor_id":2,"ambient_light":19.0,"temperature":12.4,"date":"2020-12-22T10:11:17.000+00:00","a_pressure":1008.0},{"id":84,"sensor_id":3,"ambient_light":18.0,"temperature":-0.4,"date":"2020-12-22T10:12:00.000+00:00","a_pressure":1005.5},{"id":85,"sensor_id":4,"ambient_light":146.0,"temperature":24.6,"date":"2020-12-22T10:12:43.000+00:00","a_pressure":1006.5},{"id":86,"sensor_id":1,"ambient_light":179.0,"temperature":19.1,"date":"2020-12-22T10:13:28.000+00:00","a_pressure":1010.0},{"id":87,"sensor_id":3,"ambient_light":16.0,"temperature":-0.3,"date":"2020-12-22T10:15:25.000+00:00","a_pressure":1005.5},{"id":88,"sensor_id":4,"ambient_light":140.0,"temperature":24.6,"date":"2020-12-22T10:16:08.000+00:00","a_pressure":1006.5},{"id":89,"sensor_id":2,"ambient_light":61.0,"temperature":12.0,"date":"2020-12-22T10:17:49.000+00:00","a_pressure":1008.0},{"id":90,"sensor_id":4,"ambient_light":141.0,"temperature":24.7,"date":"2020-12-22T10:19:34.000+00:00","a_pressure":1006.5},{"id":91,"sensor_id":1,"ambient_light":173.0,"temperature":19.2,"date":"2020-12-22T10:20:19.000+00:00","a_pressure":1010.5},{"id":92,"sensor_id":2,"ambient_light":38.0,"temperature":12.3,"date":"2020-12-22T10:21:04.000+00:00","a_pressure":1008.0},{"id":93,"sensor_id":3,"ambient_light":12.0,"temperature":-0.3,"date":"2020-12-22T10:22:17.000+00:00","a_pressure":1006.0},{"id":94,"sensor_id":4,"ambient_light":144.0,"temperature":24.6,"date":"2020-12-22T10:22:59.000+00:00","a_pressure":1006.5},{"id":95,"sensor_id":1,"ambient_light":176.0,"temperature":19.3,"date":"2020-12-22T10:23:44.000+00:00","a_pressure":1010.5},{"id":96,"sensor_id":2,"ambient_light":33.0,"temperature":12.3,"date":"2020-12-22T10:24:19.000+00:00","a_pressure":1008.0},{"id":97,"sensor_id":3,"ambient_light":13.0,"temperature":-0.2,"date":"2020-12-22T10:25:42.000+00:00","a_pressure":1005.5},{"id":98,"sensor_id":4,"ambient_light":149.0,"temperature":24.6,"date":"2020-12-22T10:26:25.000+00:00","a_pressure":1006.5},{"id":99,"sensor_id":1,"ambient_light":185.0,"temperature":19.3,"date":"2020-12-22T10:27:10.000+00:00","a_pressure":1010.5},{"id":100,"sensor_id":2,"ambient_light":16.0,"temperature":12.7,"date":"2020-12-22T10:27:35.000+00:00","a_pressure":1008.0},{"id":101,"sensor_id":3,"ambient_light":15.0,"temperature":-0.2,"date":"2020-12-22T10:29:08.000+00:00","a_pressure":1005.5},{"id":102,"sensor_id":4,"ambient_light":160.0,"temperature":24.6,"date":"2020-12-22T10:29:51.000+00:00","a_pressure":1006.5},{"id":103,"sensor_id":1,"ambient_light":181.0,"temperature":19.3,"date":"2020-12-22T10:30:35.000+00:00","a_pressure":1010.5},{"id":104,"sensor_id":3,"ambient_light":21.0,"temperature":-0.3,"date":"2020-12-22T10:32:33.000+00:00","a_pressure":1006.0},{"id":105,"sensor_id":4,"ambient_light":150.0,"temperature":24.6,"date":"2020-12-22T10:33:16.000+00:00","a_pressure":1006.5},{"id":106,"sensor_id":1,"ambient_light":171.0,"temperature":19.4,"date":"2020-12-22T10:34:01.000+00:00","a_pressure":1010.5},{"id":107,"sensor_id":2,"ambient_light":9.0,"temperature":12.6,"date":"2020-12-22T10:34:06.000+00:00","a_pressure":1008.0},{"id":108,"sensor_id":3,"ambient_light":17.0,"temperature":-0.4,"date":"2020-12-22T10:35:59.000+00:00","a_pressure":1006.0},{"id":109,"sensor_id":4,"ambient_light":137.0,"temperature":24.6,"date":"2020-12-22T10:36:42.000+00:00","a_pressure":1006.5},{"id":110,"sensor_id":2,"ambient_light":7.0,"temperature":10.6,"date":"2020-12-22T10:37:22.000+00:00","a_pressure":1008.5},{"id":111,"sensor_id":3,"ambient_light":16.0,"temperature":-0.2,"date":"2020-12-22T10:39:24.000+00:00","a_pressure":1006.0},{"id":112,"sensor_id":4,"ambient_light":140.0,"temperature":24.7,"date":"2020-12-22T10:40:07.000+00:00","a_pressure":1007.0},{"id":113,"sensor_id":2,"ambient_light":11.0,"temperature":11.3,"date":"2020-12-22T10:40:37.000+00:00","a_pressure":1008.5},{"id":114,"sensor_id":1,"ambient_light":142.0,"temperature":19.1,"date":"2020-12-22T10:40:52.000+00:00","a_pressure":1011.0},{"id":115,"sensor_id":3,"ambient_light":16.0,"temperature":-0.2,"date":"2020-12-22T10:42:50.000+00:00","a_pressure":1006.0},{"id":116,"sensor_id":4,"ambient_light":140.0,"temperature":24.5,"date":"2020-12-22T10:43:33.000+00:00","a_pressure":1007.0},{"id":117,"sensor_id":2,"ambient_light":7.0,"temperature":11.3,"date":"2020-12-22T10:43:53.000+00:00","a_pressure":1009.0},{"id":118,"sensor_id":1,"ambient_light":159.0,"temperature":19.2,"date":"2020-12-22T10:44:18.000+00:00","a_pressure":1011.0},{"id":119,"sensor_id":3,"ambient_light":20.0,"temperature":-0.2,"date":"2020-12-22T10:46:15.000+00:00","a_pressure":1006.0},{"id":120,"sensor_id":2,"ambient_light":7.0,"temperature":10.0,"date":"2020-12-22T10:47:08.000+00:00","a_pressure":1009.0},{"id":121,"sensor_id":1,"ambient_light":145.0,"temperature":19.1,"date":"2020-12-22T10:47:43.000+00:00","a_pressure":1011.0},{"id":122,"sensor_id":3,"ambient_light":26.0,"temperature":-0.1,"date":"2020-12-22T10:49:41.000+00:00","a_pressure":1006.0},{"id":123,"sensor_id":4,"ambient_light":133.0,"temperature":23.8,"date":"2020-12-22T10:50:24.000+00:00","a_pressure":1007.0},{"id":124,"sensor_id":1,"ambient_light":143.0,"temperature":19.0,"date":"2020-12-22T10:51:09.000+00:00","a_pressure":1011.0},{"id":125,"sensor_id":2,"ambient_light":14.0,"temperature":9.5,"date":"2020-12-22T10:53:39.000+00:00","a_pressure":1009.0},{"id":126,"sensor_id":4,"ambient_light":138.0,"temperature":23.8,"date":"2020-12-22T10:53:49.000+00:00","a_pressure":1007.0},{"id":127,"sensor_id":1,"ambient_light":153.0,"temperature":19.1,"date":"2020-12-22T10:54:34.000+00:00","a_pressure":1011.5},{"id":128,"sensor_id":3,"ambient_light":15.0,"temperature":-0.3,"date":"2020-12-22T10:56:32.000+00:00","a_pressure":1006.0},{"id":129,"sensor_id":2,"ambient_light":23.0,"temperature":9.2,"date":"2020-12-22T10:56:55.000+00:00","a_pressure":1009.0},{"id":130,"sensor_id":4,"ambient_light":135.0,"temperature":23.8,"date":"2020-12-22T10:57:15.000+00:00","a_pressure":1007.0},{"id":131,"sensor_id":1,"ambient_light":158.0,"temperature":19.0,"date":"2020-12-22T10:58:00.000+00:00","a_pressure":1011.5},{"id":132,"sensor_id":3,"ambient_light":21.0,"temperature":-0.2,"date":"2020-12-22T10:59:57.000+00:00","a_pressure":1006.0},{"id":133,"sensor_id":2,"ambient_light":27.0,"temperature":8.5,"date":"2020-12-22T11:00:10.000+00:00","a_pressure":1009.0},{"id":134,"sensor_id":4,"ambient_light":133.0,"temperature":23.8,"date":"2020-12-22T11:00:40.000+00:00","a_pressure":1007.0}]